firethorn/__init__.py
firethorn/pyfirethorn.py
firethorn/config/__init__.py
firethorn/config/firethorn_config.py
firethorn/config/resources.py
firethorn/core/__init__.py
firethorn/core/account.py
firethorn/core/firethorn_engine.py
firethorn/core/query_engine.py
firethorn/core/setup_engine.py
firethorn/models/__init__.py
firethorn/models/column.py
firethorn/models/identity.py
firethorn/models/query.py
firethorn/models/resource.py
firethorn/models/schema.py
firethorn/models/table.py
firethorn/models/adql/__init__.py
firethorn/models/adql/adql_column.py
firethorn/models/adql/adql_resource.py
firethorn/models/adql/adql_schema.py
firethorn/models/adql/adql_table.py
firethorn/models/adql_query/__init__.py
firethorn/models/adql_query/adql_query.py
firethorn/models/base/__init__.py
firethorn/models/base/base_column.py
firethorn/models/base/base_object.py
firethorn/models/base/base_resource.py
firethorn/models/base/base_schema.py
firethorn/models/base/base_table.py
firethorn/models/ivoa/__init__.py
firethorn/models/ivoa/ivoa_column.py
firethorn/models/ivoa/ivoa_resource.py
firethorn/models/ivoa/ivoa_schema.py
firethorn/models/ivoa/ivoa_table.py
firethorn/models/jdbc/__init__.py
firethorn/models/jdbc/jdbc_column.py
firethorn/models/jdbc/jdbc_resource.py
firethorn/models/jdbc/jdbc_schema.py
firethorn/models/jdbc/jdbc_table.py
firethorn/tap/__init__.py
firethorn/tap/voQuery.py
firethorn/utils/__init__.py
firethorn/utils/html_functions.py
firethorn/utils/string_functions.py
firethorn/utils/type_helpers.py
firethorn-0.1.1.dist-info/DESCRIPTION.rst
firethorn-0.1.1.dist-info/METADATA
firethorn-0.1.1.dist-info/RECORD
firethorn-0.1.1.dist-info/WHEEL
firethorn-0.1.1.dist-info/metadata.json
firethorn-0.1.1.dist-info/top_level.txt
