Metadata-Version: 2.0
Name: firethorn
Version: 0.1.1
Summary: A python suite for firethorn, and vo services (TAP)
Home-page: http://wfau.metagrid.co.uk/code/firethorn
Author: Stelios Voutsinas
Author-email: stv@roe.ac.uk
License: BSD
Keywords: firethorn vo
Platform: UNKNOWN
Classifier: Development Status :: 4 - Beta
Classifier: License :: Free For Home Use
Classifier: Programming Language :: Python
Requires-Dist: numpy (>=1.4.0)
Requires-Dist: astropy (>=0.4.1)
Requires-Dist: requests
